bq_schema/__init__.py
bq_schema/bigquery_table.py
bq_schema/dataclass_converter.py
bq_schema/py.typed
bq_schema/row_transformer.py
bq_schema/schema_converter.py
bq_schema/cli/bigquery_connection.py
bq_schema/cli/convert_table.py
bq_schema/cli/migrate_tables.py
bq_schema/migration/__init__.py
bq_schema/migration/models.py
bq_schema/migration/schema_diff.py
bq_schema/migration/table_finder.py
bq_schema/types/__init__.py
bq_schema/types/big_query_field_modes.py
bq_schema/types/big_query_types.py
bq_schema/types/type_mapping.py
bq_schema/types/type_parser.py
bq_schema-0.6.3.dist-info/entry_points.txt
bq_schema-0.6.3.dist-info/LICENSE
bq_schema-0.6.3.dist-info/WHEEL
bq_schema-0.6.3.dist-info/METADATA
bq_schema-0.6.3.dist-info/RECORD
